tapioca_ssllabs/__init__.py
tapioca_ssllabs/exceptions.py
tapioca_ssllabs/resource_mapping.py
tapioca_ssllabs/tapioca_ssllabs.py
tapioca_ssllabs-0.6.dist-info/DESCRIPTION.rst
tapioca_ssllabs-0.6.dist-info/METADATA
tapioca_ssllabs-0.6.dist-info/RECORD
tapioca_ssllabs-0.6.dist-info/WHEEL
tapioca_ssllabs-0.6.dist-info/metadata.json
tapioca_ssllabs-0.6.dist-info/top_level.txt
